verisnap/__init__.py
verisnap/main.py
verisnap-0.1.1.dist-info/LICENSE.txt
verisnap-0.1.1.dist-info/METADATA
verisnap-0.1.1.dist-info/WHEEL
verisnap-0.1.1.dist-info/top_level.txt
verisnap-0.1.1.dist-info/RECORD
