Metadata-Version: 2.1
Name: verisnap
Version: 0.1.1
Summary: A tool to create directory snapshots with size-based file copying or symlinking
Home-page: https://github.com/Chirobocea/verisnap
Author: Mihail Chirobocea
Author-email: mihail.chirobocea@s.unibuc.ro
Classifier: Programming Language :: Python :: 3
Classifier: License :: OSI Approved :: MIT License
Classifier: Operating System :: OS Independent
Requires-Python: >=3.6
License-File: LICENSE.txt
Requires-Dist: winshell>=0.6
Requires-Dist: pywin32>=306
